{
  "author": "Nayan",
  "version": "1.5.7",
  "autoRestart": true,
  "developermode": false,
  "language": "en",
  "notification": true,
  "approval": false,
  "BOTNAME": "ğ™¼ğ™¸ğ™½ğ™½ğ™¸ğ™´ ğš‡ğ™°ğ™·ğ™´ğ™³",
  "PREFIX": "/",
  "OPERATOR": [
    "61557669334326",
    "100089333225860",
    "100006070429351",
    ""
  ],
  "ADMINBOT": [
    "100006070429351",
    "61557669334326",
    "",
    ""
  ],
  "OWNER": ["100000959749712"], 
  "APPROVED": [],
  "disabledcmds": [
  ],
  "disabledevents": [],
  "note": "make sure that the bot name you entered is all lowercase",
  "notice": " dont cng auther name and owner uid. otherwise bot not working"
}
